[{"task":"P-564900 - Stonebridge Sydney Office AV - Fit-off & Commission","progress":0.5,"start":"2026-06-10T09:00:00Z","end":"2026-06-19T17:00:00Z","priority":5,"manager":"Chris Burton"},{"task":"P-565249 Gilbert + Tobin - Sydney Meeting Room","progress":0.0,"start":"2026-06-19T09:00:00Z","end":"2026-06-19T17:00:00Z","priority":5,"manager":"Matt Bowcock"},{"task":"P-565255 Equinix SY3 Displays","progress":0.0,"start":"2026-06-22T09:00:00Z","end":"2026-06-22T17:00:00Z","priority":5,"manager":"Matt Bowcock"},{"task":"P-564812 Equinix Conference Room","progress":0.0,"start":"2026-06-22T09:00:00Z","end":"2026-06-22T17:00:00Z","priority":5,"manager":"Matt Bowcock"},{"task":"P-564813 Equinix Small conference room","progress":0.0,"start":"2026-06-23T09:00:00Z","end":"2026-06-23T17:00:00Z","priority":5,"manager":"Matt Bowcock"},{"task":"P-564809 Equinix SY9 Main Conference Room","progress":0.0,"start":"2026-06-23T09:00:00Z","end":"2026-06-23T17:00:00Z","priority":5,"manager":"Matt Bowcock"},{"task":"P-564943 Canva CTV2 Upgrades","progress":0.0,"start":"2026-06-25T09:00:00Z","end":"2026-06-26T17:00:00Z","priority":5,"manager":"Matt Bowcock"},{"task":"P-546612 Ausgrid Muswellbrook","progress":0.6,"start":"2026-05-18T09:00:00Z","end":"2026-06-26T17:00:00Z","priority":5,"manager":"Matt Bowcock"},{"task":"P-564946 - Sheldon Flex Co-working - fit-off","progress":0.8,"start":"2026-05-20T09:00:00Z","end":"2026-06-26T17:00:00Z","priority":5,"manager":"Chris Burton"},{"task":"DoH / NWOW - Yaradang Level 8 - Install","progress":0.25,"start":"2026-06-03T09:00:00Z","end":"2026-06-26T17:00:00Z","priority":5,"manager":"Chris Burton"},{"task":"P-565096 DMS SYD90 Data Centre Fitoff","progress":0.0,"start":"2026-05-25T09:00:00Z","end":"2026-06-29T17:00:00Z","priority":5,"manager":"Chris Burton"},{"task":"P-546655 Team Super Newcastle Office Tech Upgrade","progress":0.0,"start":"2026-06-29T09:00:00Z","end":"2026-07-03T17:00:00Z","priority":5,"manager":"Matt Bowcock"},{"task":"P-565052 Hireup 321 Kent St","progress":0.0,"start":"2026-07-06T09:00:00Z","end":"2026-07-10T17:00:00Z","priority":5,"manager":"Matt Bowcock"},{"task":"P-565000 Alteris Town Hall Update","progress":0.0,"start":"2026-07-13T09:00:00Z","end":"2026-07-16T17:00:00Z","priority":5,"manager":"Chris Burton"},{"task":"P-565186 Pet Circle Office Fitout","progress":0.0,"start":"2026-07-20T09:00:00Z","end":"2026-07-24T17:00:00Z","priority":5,"manager":"Matt Bowcock"},{"task":"P-564996 Climatech Artarmon Meeting Room","progress":0.0,"start":"2026-07-27T09:00:00Z","end":"2026-07-27T17:00:00Z","priority":5,"manager":"Matt Bowcock"},{"task":"P-565285 Tourism Australia Marketing Meeting Room","progress":0.0,"start":"2026-07-28T09:00:00Z","end":"2026-07-28T17:00:00Z","priority":5,"manager":"Matt Bowcock"},{"task":"P-564863 Ausgrid Silverwater","progress":0.1,"start":"2026-07-06T09:00:00Z","end":"2026-08-21T17:00:00Z","priority":5,"manager":"Matt Bowcock"},{"task":"P-546726 - Ausgrid EOL Refresh","progress":0.7,"start":"2026-05-18T09:00:00Z","end":"2026-09-21T17:00:00Z","priority":5,"manager":"Matt Bowcock"},{"task":"DHDA / NWOW - Parramatta","progress":0.0,"start":"2026-08-17T09:00:00Z","end":"2026-09-24T17:00:00Z","priority":5,"manager":"Chris Burton"},{"task":"P-565109 KPMG Canberra","progress":0.0,"start":"2026-09-28T09:00:00Z","end":"2026-10-16T17:00:00Z","priority":5,"manager":"Matt Bowcock"},{"task":"DHDA / NWOW - Yaradang Level 10 - Early Comms Access","progress":0.0,"start":"2026-10-20T09:00:00Z","end":"2026-10-20T17:00:00Z","priority":5,"manager":"Chris Burton"},{"task":"Clayton Utz Canberra ","progress":0.0,"start":"2026-08-10T09:00:00Z","end":"2026-10-30T17:00:00Z","priority":5,"manager":"Matt Bowcock"},{"task":"P-565115 KPMG Parramatta","progress":0.0,"start":"2026-10-19T09:00:00Z","end":"2026-10-30T17:00:00Z","priority":5,"manager":"Matt Bowcock"},{"task":"P-565160 KPMG Newcastle","progress":0.0,"start":"2026-11-02T09:00:00Z","end":"2026-11-06T17:00:00Z","priority":5,"manager":"Matt Bowcock"},{"task":"DHDA / NWOW - Yaradang Level 10 - Install","progress":0.0,"start":"2026-10-28T09:00:00Z","end":"2026-11-20T17:00:00Z","priority":5,"manager":"Chris Burton"},{"task":"DHDA / NWOW - Yaradang Level 10 - Staff occupation","progress":0.0,"start":"2026-11-23T09:00:00Z","end":"2026-11-23T17:00:00Z","priority":5,"manager":"Chris Burton"},{"task":"P-565115 KPMG Sydney","progress":0.0,"start":"2026-11-09T09:00:00Z","end":"2026-12-18T17:00:00Z","priority":5,"manager":"Matt Bowcock"},{"task":"P-546342 Canva 8 Kippax","progress":0.03,"start":"2026-05-18T09:00:00Z","end":"2026-12-18T17:00:00Z","priority":5,"manager":"Matt Bowcock"}]